jrpyprogramming/__init__.py
jrpyprogramming/__version__.py
jrpyprogramming/data/data1.csv
jrpyprogramming/data/data2.csv
jrpyprogramming/data/data2.xlsx
jrpyprogramming/data/data3.csv
jrpyprogramming/data/data3.txt
jrpyprogramming/data/data4.csv
jrpyprogramming/data/data5.csv
jrpyprogramming/data/experiment.csv
jrpyprogramming/data/genome.csv
jrpyprogramming/data/movies.zip
jrpyprogramming/data.py
jrpyprogramming/vignettes/practical1.pdf
jrpyprogramming/vignettes/practical2.pdf
jrpyprogramming/vignettes/practical3.pdf
jrpyprogramming/vignettes/practical4.pdf
jrpyprogramming/vignettes/practical5.pdf
jrpyprogramming/vignettes/solutions1.pdf
jrpyprogramming/vignettes/solutions2.pdf
jrpyprogramming/vignettes/solutions3.pdf
jrpyprogramming/vignettes/solutions4.pdf
jrpyprogramming/vignettes/solutions5.pdf
jrpyprogramming/vignettes.py
jrpyprogramming-0.2.2.dist-info/METADATA
jrpyprogramming-0.2.2.dist-info/WHEEL
jrpyprogramming-0.2.2.dist-info/RECORD
